{
  "disponibilitesProf": {

  "disponibilitesCoursELE": [
    {
      "id": "lundi9-10",
      "name": "Lundi 9h-10h30"
    },
    {
      "id": "lundi10-12",
      "name": "Lundi 10h30-12h"
    },
    {
      "id": "lundi19-20h",
      "name": "Lundi 19h-20h30"
    },
    {
      "id": "mardi9-10",
      "name": "Mardi 9h-10h30"
    },
    {
      "id": "mardi10-12",
      "name": "Mardi 10h30-12h"
    },
    {
      "id": "mardi19-20h",
      "name": "Mardi 19h-20h30"
    },
    {
      "id": "mercredi9-10",
      "name": "Mercredi 9h-10h30"
    },
    {
      "id": "mercredi10-12",
      "name": "Mercredi 10h30-12h"
    },
    {
      "id": "mercredi19-20h",
      "name": "Mercredi 19h-20h30"
    },
    {
      "id": "jeudi9-10",
      "name": "Jeudi 9h-10h30"
    },
    {
      "id": "jeudi10-12",
      "name": "Jeudi 10h30-12h"
    },
    {
      "id": "jeudi19-20h",
      "name": "Jeudi 19h-20h30"
    },
    {
      "id": "vendredi9-10",
      "name": "Vendredi 9h-10h30"
    },
    {
      "id": "vendredi10-12",
      "name": "Vendredi 10h30-12h"
    },
    {
      "id": "vendredi19-20h",
      "name": "Vendredi 19h-20h30"
    }
  ],
    "disponibilitesCoursEnglishInter": [
        {
          "id": "lundi9-10",
          "name": "Lundi 9h-10h30"
        },
        {
          "id": "lundi10-12",
          "name": "Lundi 10h30-12h"
        },
        {
          "id": "lundi19-20h",
          "name": "Lundi 19h-20h30"
        },
        {
          "id": "mardi9-10"
        , "name": "Mardi 9h-10h30"
        }, {
          "id": "mardi10-12",
          "name": "Mardi 10h30-12h"
        },
        {
          "id": "mardi19-20h",
          "name": "Mardi 19h-20h30"
        },
        {
          "id": "mercredi9-10",
          "name": "Mercredi 9h-10h30"
        },
        {
          "id": "mercredi10-12",
          "name": "Mercredi 10h30-12h"
        },
        {
          "id": "mercredi19-20h",
          "name": "Mercredi 19h-20h30"
        },
        {
          "id": "jeudi9-10",
          "name": "Jeudi 9h-10h30"
        },
        {
          "id": "jeudi10-12",
          "name": "Jeudi 10h30-12h"
        }, {
          "id": "jeudi19-20h",
          "name": "Jeudi 19h-20h30"
        },
        {
          "id": "vendredi9-10",
          "name": "Vendredi 9h-10h30"
        },
        {
          "id": "vendredi10-12",
          "name": "Vendredi 10h30-12h"
        },
        {
          "id": "vendredi19-20h",
          "name": "Vendredi 19h-20h30"
        }
      ],
    "disponibilitesCoursEnglishAdvanced": [
    {
      "id": "lundi9-10",
      "name": "Lundi 9h-10h30"
    },
    {
      "id": "lundi10-12",
      "name": "Lundi 10h30-12h"
    },
    {
      "id": "mardi9-10",
      "name": "Mardi 9h-10h30"
    },
    {
      "id": "mardi10-12",
      "name": "Mardi 10h30-12h"
    },
    {
      "id": "mercredi9-10",
      "name": "Mercredi 9h-10h30"
    },
    {
      "id": "mercredi10-12",
      "name": "Mercredi 10h30-12h"
    },
    {
      "id": "jeudi9-10",
      "name": "Jeudi 9h-10h30"
    },
    {"id": "jeudi10-12",
      "name": "Jeudi 10h30-12h"
    },
    {
      "id": "vendredi9-10",
      "name": "Vendredi 9h-10h30"
    },
    {
      "id": "vendredi10-12",
      "name": "Vendredi 10h30-12h"
    }
],
    "disponibilitesCoursFLE": [
      {
        "id": "lundi9-10",
        "name": "Lundi 9h-10h30"
      },
      {
        "id": "lundi10-12",
        "name": "Lundi 10h30-12h"
      },
      {
        "id": "mardi9-10",
        "name": "Mardi 9h-10h30"
      },
      {
        "id": "mardi10-12",
        "name": "Mardi 10h30-12h"
      },
      {
        "id": "mercredi9-10",
        "name": "Mercredi 9h-10h30"
      },
      {
        "id": "mercredi10-12",
        "name": "Mercredi 10h30-12h"
      },
      {
        "id": "mercredi19-20",
        "name": "Mercredi 19h-20h30"
      },
      {
        "id": "jeudi9-10",
        "name": "Jeudi 9h-10h30"
      },
      {
        "id": "jeudi10-12",
        "name": "Jeudi 10h30-12h"
      },
      {
        "id": "vendredi9-10",
        "name": "Vendredi 9h-10h30"
      },
      {
        "id": "vendredi10-12",
        "name": "Vendredi 10h30-12h"
      }
    ],
    "disponibilitesCoursEnglishBusiness": [
      {
        "id": "lundi9-10",
        "name": "Lundi 9h-10h30"
      },
      {
        "id": "lundi10-12",
        "name": "Lundi 10h30-12h"
      },
      {
        "id": "mardi9-10",
        "name": "Mardi 9h-10h30"
      },
      {
        "id": "mardi10-12",
        "name": "Mardi 10h30-12h"
      },
      {
        "id": "mercredi9-10",
        "name": "Mercredi 9h-10h30"
      },
      {
        "id": "mercredi10-12",
        "name": "Mercredi 10h30-12h"
      },
      {
        "id": "jeudi9-10",
        "name": "Jeudi 9h-10h30"
      },
      {
        "id": "jeudi10-12",
        "name": "Jeudi 10h30-12h"
      },
      {
        "id": "vendredi9-10",
        "name": "Vendredi 9h-10h30"
      },
      {
        "id": "vendredi10-12",
        "name": "Vendredi 10h30-12h"
      }
    ],
    "disponibilitesCoursEnglishBeginner": [
      {
        "id": "lundi9-10",
        "name": "Lundi 9h-10h30"
      },
      {
        "id": "lundi10-12",
        "name": "Lundi 10h30-12h"
      },
      {
        "id": "lundi19-20h",
        "name": "Lundi 19h-20h30"
      },
      {
        "id": "mardi9-10",
        "name": "Mardi 9h-10h30"
      },
      {
        "id": "mardi10-12",
        "name": "Mardi 10h30-12h"
      },
      {
        "id": "mardi19-20h",
        "name": "Mardi 19h-20h30"
      },
      {
        "id": "mercredi9-10",
        "name": "Mercredi 9h-10h30"
      },
      {
        "id": "mercredi10-12",
        "name": "Mercredi 10h30-12h"
      },
      {
        "id": "mercredi19-20h",
        "name": "Mercredi 19h-20h30"
      },
      {
        "id": "jeudi9-10",
        "name": "Jeudi 9h-10h30"
      },
      {
        "id": "jeudi10-12",
        "name": "Jeudi 10h30-12h"
      },
      {
        "id": "jeudi19-20h",
        "name":  "Jeudi 19h-20h30"
      },
      {
        "id": "vendredi9-10",
        "name": "Vendredi 9h-10h30"
      },
      {
        "id": "vendredi10-12",
        "name": "Vendredi 10h30-12h"
      },
      {
        "id": "vendredi19-20h",
        "name": "Vendredi 19h-20h30"
      }
    ],
    "disponibilitesAyudaDeberes1":[
      {
        "id": "mardi15-17",
        "name": "Mardi 15h-17h"
      }
    ],
    "disponibilitesAyudaDeberes2":[
      {
        "id": "mardi15-17",
        "name": "Mardi 15h-17h"
      }
    ],
    "disponibilitesAyudaDeberes3":[
      {
        "id": "mardi15-17",
        "name": "Mardi 15h-17h"
      }
    ],
    "disponibilitesAyudaDeberes4":[
      {
        "id": "lundi15-17",
        "name": "Lundi 15h-17h"
      },
      {
        "id": "mercredi15-17",
        "name": "Mercredi 15h-17h"
      }
    ],
    "disponibilitesMathPrimaria4":[
      {
        "id": "lundi15-17",
        "name": "Lundi 15h-17h"
      },
      {
        "id": "mercredi17-18",
        "name": "Mercredi 17h-18h30"
      }
    ],
    "disponibilitesAyudaDeberes5":[
      {
        "id": "mercredi17-18",
        "name": "Mercredi 17h-18h30"
      }
    ],
    "disponibilitesMathPrimaria5":[
      {
        "id": "lundi17-18",
        "name": "Lundi 17h-18h30"
      }
    ],
    "disponibilitesLenguaPrimaria5":[
      {
        "id": "jeudi17-18",
        "name": "Jeudi 17h-18h30"
      }
    ],
    "disponibilitesMathPrimaria6":[
      {
        "id": "mardi17-18",
        "name": "Mardi 17h-18h30"
      }
    ],
    "disponibilitesLenguaPrimaria6":[
      {
        "id": "vendredi17-18",
        "name": "Vendredi 17h-18h30"
      }
    ],
    "disponibilitesAyudaDeberes6":[
      {
        "id": "lundi15-17",
        "name": "Lundi 15h-17h"
      },
      {
        "id": "mercredi15-17",
        "name":"Mercredi 15h-17h"
      }
    ],
    "disponibilitesCoursMathESO1":[
      {
        "id": "lundi16-17",
        "name": "Lundi 16h-17h30"
      },
      {
        "id": "jeudi16-17",
        "name": "Jeudi 16h-17h30"
      }
    ],
    "disponibilitesCoursLenguaESO1":[
      {
        "id": "mardi16-17",
        "name": "Mardi 16h-17h30"
      },
      {
        "id": "vendredi16-17",
        "name": "Vendredi 16h-17h30"
      }
    ],
    "disponibilitesCoursMathESO2":[
      {
        "id": "mardi16-17",
        "name": "Mardi 16h-17h30"
      },
      {
        "id": "vendredi16-17",
        "name": "Vendredi 16h-17h30"
      }
    ],
    "disponibilitesCoursLenguaESO2":[
      {
        "id": "lundi16-17",
        "name": "Lundi 16h-17h30"
      },
      {"id": "jeudi16-17",
        "name": "Jeudi 16h-17h30"
      }
    ],
    "disponibilitesCoursMathESO3":[
      {
        "id": "lundi17-19",
        "name": "Lundi 17h30-19h"
      },
      {
        "id": "jeudi17-19",
        "name": "Jeudi 17h30-19h"
      }
    ],
    "disponibilitesCoursLenguaESO3":[
      {
        "id": "mardi17-19",
        "name": "Mardi 17h30-19h"
      },
      {
        "id": "vendredi17-19",
        "name": "Vendredi 17h30-19h"
      }
    ],
    "disponibilitesCoursFisicaESO3":[
      {
        "id": "mercredi16-17",
        "name": "Mercredi 16h-17h30"
      }
    ],
    "disponibilitesCoursFisicaESO4":[
      {
        "id": "mercredi17-19",
        "name": "Mercredi 17h30-19h"
      }
    ],
    "disponibilitesCoursMathESO4":[
      {
        "id": "mardi17-19",
        "name": "Mardi 17h30-19h"
      },
      {
        "id": "vendredi17-19",
        "name": "Vendredi 17h30-19h"
      }
    ],
    "disponibilitesCoursLenguaESO4":[
      {
        "id": "lundi17-19",
        "name": "Lundi 17h30-19h"
      },
      {
        "id": "jeudi17-19",
        "name": "Jeudi 17h30-19h"
      }
    ],
    "disponibilitesCoursMathBacEsp1": [
      {
        "id": "lundi19-20",
        "name": "Lundi 19h-20h30"
      },
      {
        "id": "mercredi19-20",
        "name": "Mercredi 19h-20h30"
      }
    ],
    "disponibilitesCoursEcoBacEsp2": [
      {
        "id": "lundi19-20",
        "name": "Lundi 19h-20h30"
      },
      {
        "id": "mercredi19-20",
        "name": "Mercredi 19h-20h30"
      },
      {
        "id": "jeudi19-20",
        "name": "Jeudi 19h-20h30"
      }
    ],
    "disponibilitesCoursLiteraturaBacEsp1": [
      {
        "id": "mardi19-20",
        "name": "Mardi 19h-20h30"
      }
    ],
    "disponibilitesCoursLiteraturaBacEsp2": [
      {
        "id": "vendredi19-20",
        "name": "Vendredi 19h-20h30"
      }
    ],
    "disponibilitesCoursMathBacEsp2": [
      {
        "id": "vendredi19-20",
        "name": "Vendredi 19h-20h30"
      }
    ],
    "disponibilitesCoursTestMissionCP": [
      {
        "id": "mercredi14-16",
        "name": "Mercredi 14h-16h"
      }
    ],
    "disponibilitesCoursFr4eme": [
      {
        "id": "mardi16-17",
        "name": "Mardi 16h-17h30"
      },
      {
        "id": "mercredi17-19",
        "name": "Mercredi 17h30-19h"
      },
      {
        "id": "vendredi16-17",
        "name": "Vendredi 16h-17h30"
      }
    ],
    "disponibilitesCoursMath4eme": [
      {
        "id": "lundi16-17",
        "name": "Lundi 16h-17h30"
      },
      {
        "id": "jeudi17-19",
        "name": "Jeudi 17h30-19h"
      }
    ],
    "disponibilitesCoursFr6eme": [
      {
        "id": "lundi16-17",
        "name": "Lundi 16h-17h30"
      },
      {
        "id": "mercredi14-16",
        "name": "Mercredi 14h30-16h"
      }
    ],
    "disponibilitesCoursMath6eme": [
      {
        "id": "mardi17-19",
        "name": "Mardi 17h30-19h"
      }
    ],
    "disponibilitesCoursMath3eme": [
      {
        "id": "lundi17-19",
        "name": "Lundi 17h30-19h"
      },
      {
        "id": "mercredi17-19",
        "name": "Mercredi 17h30-19h"
      }
    ],
    "disponibilitesCoursFr3eme": [
      {
        "id": "mardi17-19",
        "name": "Mardi 17h30-19h"
      },
      {
        "id": "mercredi19-20",
        "name": "Mercredi 19h-20h30"
      },
      {
        "id": "jeudi17-19",
        "name": "Jeudi 17h30-19h"
      },
      {
        "id": "vendredi17-19",
        "name": "Vendredi 17h30-19h"
      }
    ],
    "disponibilitesCoursPhys3eme": [
      {
        "id": "mardi19-20",
        "name": "Mardi 19h-20h30"
      },
      {
        "id": "vendredi17-19",
        "name": "Vendredi 17h30-19h"
      }
    ],
    "disponibilitesCoursFr5eme": [
      {
        "id": "lundi17-19",
        "name": "Lundi 17h30-19h"
      },
      {
        "id": "mercredi16-17",
        "name": "Mercredi 16h-17h30"
      }
    ],
    "disponibilitesCoursMath5eme": [
      {
        "id": "vendredi16-17",
        "name": "Vendredi 16h-17h30"
      }
    ],
    "disponibilitesCoursMath2nde": [
      {
        "id": "lundi19-20",
        "name": "Lundi 19h-20h30"
      }
    ],
    "disponibilitesCoursFr2nde": [
      {
        "id": "mardi19-20",
        "name": "Mardi 19h-20h30"
      }
    ],
    "disponibilitesCoursPhys2nde": [
      {
        "id": "jeudi19-20",
        "name": "Jeudi 19h-20h30"
      },
      {
        "id": "vendredi19-20",
        "name": "Vendredi 19h-20h30"
      }
    ],
    "disponibilitesCoursFr1ere": [
      {
        "id": "lundi19-20",
        "name": "Lundi 19h-20h30"
      },
      {
        "id": "samedi14-17",
        "name": "Samedi 14h-17h"
      }
    ],
    "disponibilitesCoursMath1ereES": [
      {
        "id": "mercredi19-20",
        "name": "Mercredi 19h-20h30"
      }
    ],
    "disponibilitesCoursMathTS": [
      {
        "id": "jeudi19-20",
        "name": "Jeudi 19h-20h30"
      },
      {
        "id": "samedi14-17",
        "name": "Samedi 14h-17h"
      }
    ],
    "disponibilitesCoursPhysTS": [
      {
        "id": "samedi14-17",
        "name": "Samedi 14h-17h"
      }
    ],
    "disponibilitesCoursEcoTES": [
      {
        "id": "samedi14-17",
        "name": "Samedi 14h-17h"
      }
    ],
    "disponibilitesCoursEcoDroitSTMG": [
      {
        "id": "samedi14-17",
        "name": "Samedi 14h-17h"
      }
    ],

    "disponibilitesCoursMathCE2": [
      {
        "id": "lundi16-17",
        "name": "Lundi 16h-17h30"
      }
    ],
    "disponibilitesCoursFrCE2": [
      {
        "id": "mardi17-19",
        "name": "Mardi 17h30-19h"
      },
      {
        "id": "jeudi16-17",
        "name": "Jeudi 16h-17h30"
      },
      {
        "id": "vendredi16-17",
        "name": "Vendredi 16h-17h30"
      }
    ],
    "disponibilitesCoursTestMissionCE2": [
      {
        "id": "mercredi16-18",
        "name": "Mercredi 16h-18h"
      },
      {
        "id": "samedi11-13",
        "name": "Samedi 11h-13h"
      }
    ],
    "disponibilitesCoursFrCE1": [
      {
        "id": "lundi16-17",
        "name": "Lundi 16h-17h30"
      }
    ],
    "disponibilitesCoursMathCE1": [
      {
        "id": "mardi16-17",
        "name": "Mardi 16h-17h30"
      },
      {
        "id": "jeudi16-17",
        "name": "Jeudi 16h-17h30"
      },
      {
        "id": "vendredi16-17",
        "name": "Vendredi 16h-17h30"
      }
    ],
    "disponibilitesCoursTestMissionCE1": [
      {
        "id": "mercredi16-18",
        "name": "Mercredi 16h-18h"
      },
      {
        "id": "samedi11-13",
        "name": "Samedi 11h-13h"
      }
    ],
    "disponibilitesCoursMathCM2": [
      {
        "id": "lundi17-19",
        "name": "Lundi 17h30-19h"
      }
    ],
    "disponibilitesCoursFrCM2": [
      {
        "id": "mardi17-19",
        "name": "Mardi 17h30-19h"
      },
      {
        "id": "jeudi17-19",
        "name": "Jeudi 17h30-19h"
      },
      {
        "id": "vendredi17-19",
        "name": "Vendredi 17h30-19h"
      }
    ],
    "disponibilitesCoursTestMissionMathCM2": [
      {
        "id": "mercredi14-15",
        "name": "Mercredi 14h-15h30"
      },
      {
        "id": "samedi9-10",
        "name": "Samedi 9h-10h30"
      }
    ],
    "disponibilitesCoursTestMissionFrCM2": [
      {
        "id": "mercredi15-17",
        "name": "Mercredi 15h30-17h"
      },
      {
        "id": "samedi10-12",
        "name": "Samedi 10h30-12h"
      }
    ],
    "disponibilitesCoursFrCM1": [
      {
        "id": "lundi17-19",
        "name": "Lundi 17h30-19h"
      }
    ],
    "disponibilitesCoursMathCM1": [
      {
        "id": "mardi17-19",
        "name": "Mardi 17h30-19h"
      },
      {
        "id": "jeudi17-19",
        "name": "Jeudi 17h30-19h"
      },
      {
        "id": "vendredi17-19",
        "name": "Vendredi 17h30-19h"
      }
    ],
    "disponibilitesCoursTestMissionMathCM1": [
      {
        "id": "mercredi15-17",
        "name": "Mercredi 15h30-17h"
      },
      {
        "id": "samedi10-12",
        "name": "Samedi 10h30-12h"
      }
    ],
    "disponibilitesCoursTestMissionFrCM1": [
      {
        "id": "mercredi14-15",
        "name": "Mercredi 14h-15h30"
      },
      {
        "id": "samedi9-10",
        "name": "Samedi 9h-10h30"
      }
    ],
    "disponibilitesCoursIELTS": [
      {
        "id": "samedi10-13",
        "name": "Samedi 10h-13h"
      }
    ],
    "disponibilitesCoursTOEFL": [
      {
        "id": "samedi14-17",
        "name": "Samedi 14h-17h"
      }
    ],
    "disponibilitesSAT": [
      {
        "id": "samedi14-17",
        "name": "Samedi 14h-17h"
      }
    ]
}
}




